oc_client_provider/__init__.py
oc_client_provider/config.py
oc_client_provider/wsgi.py
oc_client_provider/app/__init__.py
oc_client_provider/app/client_counterparty.py
oc_client_provider/app/client_getter.py
oc_client_provider/app/client_tf.py
oc_client_provider/app/routes.py
oc_client_provider-1.2.1.dist-info/licenses/LICENSE
oc_client_provider-1.2.1.dist-info/METADATA
oc_client_provider-1.2.1.dist-info/WHEEL
oc_client_provider-1.2.1.dist-info/top_level.txt
oc_client_provider-1.2.1.dist-info/RECORD
