Metadata-Version: 2.4
Name: oc-client-provider
Version: 1.2.1
Summary: Client provider
License: Apache2.0
Requires-Python: >=3.6
License-File: LICENSE
Requires-Dist: oc-delivery-apps>=11.2.9
Requires-Dist: oc-orm-initializator>=1.1.0
Requires-Dist: flask
Requires-Dist: gunicorn
Requires-Dist: pytz
Requires-Dist: pyyaml
Dynamic: description
Dynamic: description-content-type
Dynamic: license
Dynamic: license-file
Dynamic: requires-dist
Dynamic: requires-python
Dynamic: summary
